.coveragerc
.gitignore
CHANGES.md
CODE_OF_CONDUCT.md
CONTRIBUTING.md
LICENSE
MANIFEST.in
Makefile
README.md
setup.cfg
setup.py
versioneer.py
ngsindex/__init__.py
ngsindex/_version.py
ngsindex/cli.py
ngsindex/utils.py
ngsindex.egg-info/PKG-INFO
ngsindex.egg-info/SOURCES.txt
ngsindex.egg-info/dependency_links.txt
ngsindex.egg-info/entry_points.txt
ngsindex.egg-info/requires.txt
ngsindex.egg-info/top_level.txt
tests/__init__.py
tests/conftest.py
tests/test_index.py
tests/test_utils.py
tests/test_index/small.bam
tests/test_index/small.bam.bai
tests/test_index/small.sam
tests/test_index/small.vcf.gz
tests/test_index/small.vcf.gz.csi
tests/test_index/small.vcf.gz.tbi
tests/test_index/small_with_unmapped.bam
tests/test_index/small_with_unmapped.bam.bai
tests/test_utils/small.bam.bai