Metadata-Version: 2.1
Name: ngsindex
Version: 0.1.5
Summary: Utilities for working with NGS index formats.
Home-page: https://github.com/jdidion/ngsindex
Author: John Didion
Author-email: github@didion.net
License: MIT
Platform: UNKNOWN
Classifier: Development Status :: 5 - Production/Stable
Classifier: Intended Audience :: Developers
Classifier: Topic :: Software Development :: Libraries :: Python Modules
Classifier: License :: OSI Approved :: MIT License
Classifier: License :: Public Domain
Classifier: Programming Language :: Python :: 3 :: Only
Classifier: Programming Language :: Python :: 3.6
